polyqr/__init__.py
polyqr/py.typed
polyqr-1.1.3.dist-info/licenses/License
polyqr-1.1.3.dist-info/METADATA
polyqr-1.1.3.dist-info/WHEEL
polyqr-1.1.3.dist-info/entry_points.txt
polyqr-1.1.3.dist-info/top_level.txt
polyqr-1.1.3.dist-info/RECORD
