Metadata-Version: 2.4
Name: polyqr
Version: 1.1.3
Summary: QR Codes as Polygons (TikZ/SVG)
Author-email: Kurt Böhm <kurbo96@gmail.com>
License-Expression: MPL-2.0
Project-URL: Repository, https://github.com/KurtBoehm/polyqr
Keywords: svg,drawing,vector,tikz,latex,qr-code
Classifier: Intended Audience :: Developers
Classifier: Programming Language :: Python :: 3
Classifier: Programming Language :: Python :: 3.11
Classifier: Programming Language :: Python :: 3.12
Classifier: Programming Language :: Python :: 3.13
Classifier: Topic :: Software Development
Classifier: Topic :: Multimedia :: Graphics
Classifier: Topic :: Text Processing :: Markup :: LaTeX
Requires-Python: >=3.11
License-File: License
Requires-Dist: qrcode
Provides-Extra: dev
Requires-Dist: numpy; extra == "dev"
Requires-Dist: cairosvg; extra == "dev"
Requires-Dist: pillow; extra == "dev"
Requires-Dist: pytest; extra == "dev"
Requires-Dist: pytest-cov; extra == "dev"
Requires-Dist: pytest-xdist; extra == "dev"
Requires-Dist: PyMuPDF; extra == "dev"
Dynamic: license-file
